swaggermap/__init__.py
swaggermap/main.py
swaggermap-1.4.1.dist-info/LICENSE
swaggermap-1.4.1.dist-info/METADATA
swaggermap-1.4.1.dist-info/WHEEL
swaggermap-1.4.1.dist-info/entry_points.txt
swaggermap-1.4.1.dist-info/top_level.txt
swaggermap-1.4.1.dist-info/RECORD
