Metadata-Version: 2.1
Name: swaggermap
Version: 1.4.1
Summary: Swaggermap
Home-page: https://github.com/kirei/swaggermap
Author: Jakob Schlyter
Author-email: jakob@kirei.se
License: BSD
Keywords: swagger,openapi
Platform: UNKNOWN
Classifier: License :: OSI Approved :: BSD License
Classifier: Programming Language :: Python :: 3 :: Only
Requires-Dist: deepdiff
Requires-Dist: requests
Requires-Dist: ruamel.yaml
Requires-Dist: setuptools
